pymceliece/__init__.py
pymceliece/__init__.pyi
pymceliece/py.typed
pymceliece/.mypy_cache/.gitignore
pymceliece/.mypy_cache/CACHEDIR.TAG
pymceliece/.mypy_cache/3.11/@plugins_snapshot.json
pymceliece/.mypy_cache/3.11/_ast.data.json
pymceliece/.mypy_cache/3.11/_ast.meta.json
pymceliece/.mypy_cache/3.11/_codecs.data.json
pymceliece/.mypy_cache/3.11/_codecs.meta.json
pymceliece/.mypy_cache/3.11/_collections_abc.data.json
pymceliece/.mypy_cache/3.11/_collections_abc.meta.json
pymceliece/.mypy_cache/3.11/_ctypes.data.json
pymceliece/.mypy_cache/3.11/_ctypes.meta.json
pymceliece/.mypy_cache/3.11/abc.data.json
pymceliece/.mypy_cache/3.11/abc.meta.json
pymceliece/.mypy_cache/3.11/array.data.json
pymceliece/.mypy_cache/3.11/array.meta.json
pymceliece/.mypy_cache/3.11/builtins.data.json
pymceliece/.mypy_cache/3.11/builtins.meta.json
pymceliece/.mypy_cache/3.11/codecs.data.json
pymceliece/.mypy_cache/3.11/codecs.meta.json
pymceliece/.mypy_cache/3.11/contextlib.data.json
pymceliece/.mypy_cache/3.11/contextlib.meta.json
pymceliece/.mypy_cache/3.11/dataclasses.data.json
pymceliece/.mypy_cache/3.11/dataclasses.meta.json
pymceliece/.mypy_cache/3.11/enum.data.json
pymceliece/.mypy_cache/3.11/enum.meta.json
pymceliece/.mypy_cache/3.11/genericpath.data.json
pymceliece/.mypy_cache/3.11/genericpath.meta.json
pymceliece/.mypy_cache/3.11/io.data.json
pymceliece/.mypy_cache/3.11/io.meta.json
pymceliece/.mypy_cache/3.11/mmap.data.json
pymceliece/.mypy_cache/3.11/mmap.meta.json
pymceliece/.mypy_cache/3.11/pathlib.data.json
pymceliece/.mypy_cache/3.11/pathlib.meta.json
pymceliece/.mypy_cache/3.11/pickle.data.json
pymceliece/.mypy_cache/3.11/pickle.meta.json
pymceliece/.mypy_cache/3.11/posixpath.data.json
pymceliece/.mypy_cache/3.11/posixpath.meta.json
pymceliece/.mypy_cache/3.11/re.data.json
pymceliece/.mypy_cache/3.11/re.meta.json
pymceliece/.mypy_cache/3.11/sre_compile.data.json
pymceliece/.mypy_cache/3.11/sre_compile.meta.json
pymceliece/.mypy_cache/3.11/sre_constants.data.json
pymceliece-0.0.3.dist-info/LICENSE
pymceliece-0.0.3.dist-info/WHEEL
pymceliece-0.0.3.dist-info/METADATA
pymceliece-0.0.3.dist-info/RECORD
