Metadata-Version: 2.3
Name: pymceliece
Version: 0.0.3
Summary: A Python wrapper for the libmceliece microlibrary
Keywords: post-quantum,cryptography,McEliece,Classic McEliece,libmceliece,pymceliece
Author-email: Jonathan Levin <pymceliece@riseup.net>
Requires-Python: >=3.6
Classifier: Development Status :: 4 - Beta
Classifier: Topic :: Security :: Cryptography
Classifier: Topic :: Security
Project-URL: Source, https://www.github.com/ondesmartenot/pymceliece
